sdgx/__init__.py
sdgx/data_loader.py
sdgx/exceptions.py
sdgx/log.py
sdgx/manager.py
sdgx/synthesizer.py
sdgx/utils.py
sdgx/cachers/__init__.py
sdgx/cachers/base.py
sdgx/cachers/disk_cache.py
sdgx/cachers/extension.py
sdgx/cachers/manager.py
sdgx/cli/__init__.py
sdgx/cli/main.py
sdgx/cli/message.py
sdgx/cli/utils.py
sdgx/data_connectors/__init__.py
sdgx/data_connectors/base.py
sdgx/data_connectors/csv_connector.py
sdgx/data_connectors/dataframe_connector.py
sdgx/data_connectors/extension.py
sdgx/data_connectors/generator_connector.py
sdgx/data_connectors/manager.py
sdgx/data_connectors/mysql_connector.py
sdgx/data_exporters/__init__.py
sdgx/data_exporters/base.py
sdgx/data_exporters/csv_exporter.py
sdgx/data_exporters/extension.py
sdgx/data_exporters/manager.py
sdgx/data_models/__init__.py
sdgx/data_models/combiner.py
sdgx/data_models/metadata.py
sdgx/data_models/relationship.py
sdgx/data_models/inspectors/__init__.py
sdgx/data_models/inspectors/base.py
sdgx/data_models/inspectors/bool.py
sdgx/data_models/inspectors/const.py
sdgx/data_models/inspectors/datetime.py
sdgx/data_models/inspectors/discrete.py
sdgx/data_models/inspectors/empty.py
sdgx/data_models/inspectors/extension.py
sdgx/data_models/inspectors/fixed_combination.py
sdgx/data_models/inspectors/i_id.py
sdgx/data_models/inspectors/manager.py
sdgx/data_models/inspectors/numeric.py
sdgx/data_models/inspectors/personal.py
sdgx/data_models/inspectors/regex.py
sdgx/data_models/inspectors/subset_relationship.py
sdgx/data_processors/__init__.py
sdgx/data_processors/base.py
sdgx/data_processors/extension.py
sdgx/data_processors/manager.py
sdgx/data_processors/filter/__init__.py
sdgx/data_processors/filter/base.py
sdgx/data_processors/filter/positive_negative.py
sdgx/data_processors/formatters/__init__.py
sdgx/data_processors/formatters/base.py
sdgx/data_processors/formatters/datetime.py
sdgx/data_processors/formatters/int.py
sdgx/data_processors/generators/__init__.py
sdgx/data_processors/generators/base.py
sdgx-0.2.4.dist-info/METADATA
sdgx-0.2.4.dist-info/WHEEL
sdgx-0.2.4.dist-info/entry_points.txt
sdgx-0.2.4.dist-info/licenses/LICENSE
sdgx-0.2.4.dist-info/licenses/NOTICE
sdgx-0.2.4.dist-info/RECORD
