Metadata-Version: 2.3
Name: sdgx
Version: 0.2.4
Summary: synthetic-data-generator
Project-URL: Source, https://github.com/hitsz-ids/synthetic-data-generator
Author: hitsz-ids
License: Apache Software License 2.0
Keywords: hitsz-ids,synthetic data
Classifier: Programming Language :: Python :: 3
Classifier: Programming Language :: Python :: 3.8
Classifier: Programming Language :: Python :: 3.9
Classifier: Programming Language :: Python :: 3.10
Classifier: Programming Language :: Python :: 3.11
Classifier: Programming Language :: Python :: 3.12
Requires-Python: >=3.9
Requires-Dist: click
Requires-Dist: cloudpickle
Requires-Dist: faker>=10
Requires-Dist: importlib-metadata
Requires-Dist: joblib>=1.4.0
Requires-Dist: loguru
Requires-Dist: matplotlib
Requires-Dist: numpy<2
Requires-Dist: openai>=1.10.0
Requires-Dist: pandas
Requires-Dist: pluggy
Requires-Dist: pyarrow
Requires-Dist: pydantic>=2
Requires-Dist: python-dotenv
Requires-Dist: pyyaml
Requires-Dist: scikit-learn<2,>=0.24
Requires-Dist: scipy
Requires-Dist: table-evaluator
Requires-Dist: torch>=2
Provides-Extra: docs
Requires-Dist: autodoc-pydantic>=2; extra == 'docs'
Requires-Dist: pydata-sphinx-theme; extra == 'docs'
Requires-Dist: sphinx; extra == 'docs'
Requires-Dist: sphinx-click; extra == 'docs'
Provides-Extra: test
Requires-Dist: coverage<7; extra == 'test'
Requires-Dist: email-validator; extra == 'test'
Requires-Dist: pytest; extra == 'test'
Requires-Dist: pytest-cov; extra == 'test'
